{"image": "25891.jpg", "en": "Unit 11", "wordlist": [{"en": "abnormal", "pron": "[æbˈnɔ:rməl] adj.", "desc": "If something is abnormal, it is strange or not normal.", "exam": "Her idea of art is a bit too <strong>abnormal </strong>for me.", "vi": "", "image": "26258.jpg", "sound": "26258.mp3"}, {"en": "bamboo", "pron": "[bæmˈbu:] n.", "desc": "Bamboo is a hard plant with thin branches and leaves.", "exam": "Outside his home, there is a lot of <strong>bamboo</strong>.", "vi": "", "image": "26259.jpg", "sound": "26259.mp3"}, {"en": "blossom", "pron": "[ˈblɑsəm] n.", "desc": "A blossom is a flower or group of flowers.", "exam": "There were colorful <strong>blossoms </strong>in the yard.", "vi": "", "image": "26260.jpg", "sound": "26260.mp3"}, {"en": "compass", "pron": "[ˈkʌmpəs] n.", "desc": "A compass is a device used to tell what direction one is going.", "exam": "A <strong>compass </strong>is an important tool to have when you are traveling.", "vi": "", "image": "26261.jpg", "sound": "26261.mp3"}, {"en": "dialect", "pron": "[ˈdaɪəlekt] n.", "desc": "A dialect is a regional variety of language showing where you are from.", "exam": "People from the U.K. have a different <strong>dialect </strong>of English from those in the U.K.", "vi": "", "image": "26262.jpg", "sound": "26262.mp3"}, {"en": "dishonest", "pron": "[dɪsˈɒnɪst] adj.", "desc": "If someone is dishonest, they do not tell the truth.", "exam": "She was being <strong>dishonest </strong>when she copied the answers from his test.", "vi": "", "image": "26263.jpg", "sound": "26263.mp3"}, {"en": "dwarf", "pron": "[dwɔːrf] n.", "desc": "A dwarf is a creature from stories that often looks like a short, hairy man.", "exam": "The <strong>dwarf </strong>had a pleasant look on his face.", "vi": "", "image": "26264.jpg", "sound": "26264.mp3"}, {"en": "ecosystem", "pron": "[i:kousɪstəm] n.", "desc": "An ecosystem is a group of plants and animals in an area.", "exam": "The river&rsquo;s <strong>ecosystem </strong>not only includes fish but other insects and plants too.", "vi": "", "image": "26265.jpg", "sound": "26265.mp3"}, {"en": "fatal", "pron": "[ˈfeɪtl] adj.", "desc": "If something is fatal, it causes death.", "exam": "They passed away in a <strong>fatal </strong>car crash.", "vi": "", "image": "26266.jpg", "sound": "26266.mp3"}, {"en": "impatient", "pron": "[ɪmˈpeɪʃənt] adj.", "desc": "If someone is impatient, they are not able to wait for things.", "exam": "Bob was so <strong>impatient </strong>that he could barely wait for the light to turn green.", "vi": "", "image": "26267.jpg", "sound": "26267.mp3"}, {"en": "leaf", "pron": "[li:f] n.", "desc": "A leaf is the flat green thing on trees or bushes.", "exam": "In the fall, the <strong>leaves </strong>on the trees change colors.", "vi": "", "image": "26268.jpg", "sound": "26268.mp3"}, {"en": "manuscript", "pron": "[ˈmӕnjəskript] n.", "desc": "A manuscript is an old book or paper written by hand.", "exam": "The <strong>manuscript </strong>was written over 150 years ago.", "vi": "", "image": "26269.jpg", "sound": "26269.mp3"}, {"en": "marsh", "pron": "[mɑːrʃ] n.", "desc": "A marsh is a type of wet land covered with grasses and short plants.", "exam": "The <strong>marsh </strong>looked so lovely against the mountains.", "vi": "", "image": "26270.jpg", "sound": "26270.mp3"}, {"en": "patience", "pron": "[ˈpeɪʃəns] n.", "desc": "Patience is the ability to wait for something without becoming upset.", "exam": "Sue&rsquo;s <strong>patience </strong>was rewarded by catching her very first fish.", "vi": "", "image": "26271.jpg", "sound": "26271.mp3"}, {"en": "perfume", "pron": "[pəˈ:rfjuːm] n.", "desc": "Perfume is a good-smelling liquid that girls wear.", "exam": "When she wore her <strong>perfume</strong>, everyone said she smelled great.", "vi": "", "image": "26272.jpg", "sound": "26272.mp3"}, {"en": "pond", "pron": "[pɒnd] n.", "desc": "A pond is a very small area of water.", "exam": "The ducks swam in the <strong>pond</strong>.", "vi": "", "image": "26273.jpg", "sound": "26273.mp3"}, {"en": "proverb", "pron": "[ˈprɒvəːrb] n.", "desc": "A proverb is a short saying that tells you something important.", "exam": "The <strong>proverb </strong>&ldquo;egg on your face&rdquo; means you&rsquo;ve done something embarrassing.", "vi": "", "image": "26274.jpg", "sound": "26274.mp3"}, {"en": "pursuit", "pron": "[pərsuːt] n.", "desc": "A pursuit is a chase.", "exam": "The dinosaur was in <strong>pursuit </strong>of the caveman.", "vi": "", "image": "26275.jpg", "sound": "26275.mp3"}, {"en": "recite", "pron": "[rɪˈsaɪt] v.", "desc": "To recite something means to repeat or say aloud in front of a group.", "exam": "Katie <strong>recited </strong>the Pledge of Allegiance in class.", "vi": "", "image": "26276.jpg", "sound": "26276.mp3"}, {"en": "wilderness", "pron": "[ˈwɪldə:rnɪs] n.", "desc": "A wilderness is an area where no people live.", "exam": "If you are not careful, you can get lost in the <strong>wilderness</strong>.", "vi": "", "image": "26277.jpg", "sound": "26277.mp3"}], "exercise": [{"en": "Exercise 1", "story": "<h4>Part A: Choose the right word for the given definition.</h4><ol><li class=\"answer-the-questions-section\" answer-index=\"2\">to speak openly<ul class=\"ul-choose-answer\"><li>a. abnormal</li><li>b. compass</li><li>c. recite</li><li>d. pursuit</li></ul></li><li class=\"answer-the-questions-section\" answer-index=\"1\">capable of causing death<ul class=\"ul-choose-answer\"><li>a. wilderness</li><li>b. fatal</li><li>c. impatient</li><li>d. blossom</li></ul></li><li class=\"answer-the-questions-section\" answer-index=\"0\">a group of living things<ul class=\"ul-choose-answer\"><li>a. ecosystem</li><li>b. manuscript</li><li>c. dwarf</li><li>d. bamboo</li></ul></li><li class=\"answer-the-questions-section\" answer-index=\"2\">the ability to wait without getting upset<ul class=\"ul-choose-answer\"><li>a. proverb</li><li>b. marsh</li><li>c. patience</li><li>d. abnormal</li></ul></li><li class=\"answer-the-questions-section\" answer-index=\"3\">a very short character in stories<ul class=\"ul-choose-answer\"><li>a. leaf</li><li>b. dialect</li><li>c. recite</li><li>d. dwarf</li></ul></li></ol><h4>Part B: Choose the right definition for the given word.</h4><ol><li class=\"answer-the-questions-section\" answer-index=\"3\">manuscript<ul class=\"ul-choose-answer\"><li>a. grass with thin branches</li><li>b. an area not settled by people</li><li>c. being able to wait</li><li>d. an old book</li></ul></li><li class=\"answer-the-questions-section\" answer-index=\"0\">proverb<ul class=\"ul-choose-answer\"><li>a. a short saying</li><li>b. a device used to tell direction</li><li>c. a small area of water</li><li>d. to say something aloud</li></ul></li><li class=\"answer-the-questions-section\" answer-index=\"0\">pursuit<ul class=\"ul-choose-answer\"><li>a. a chase</li><li>b. not normal</li><li>c. a book</li><li>d. speaking</li></ul></li><li class=\"answer-the-questions-section\" answer-index=\"1\">dialect<ul class=\"ul-choose-answer\"><li>a. can cause death</li><li>b. a different way of speaking</li><li>c. a flat green thing</li><li>d. a creature from stories</li></ul></li><li class=\"answer-the-questions-section\" answer-index=\"1\">marsh<ul class=\"ul-choose-answer\"><li>a. flowers</li><li>b. wet land</li><li>c. lies</li><li>d. living things</li></ul></li></ol>", "sound": ""}, {"en": "Exercise 2", "story": "<h4>Choose the answer that best fits the question.</h4><ol><li class=\"answer-the-questions-section\" answer-index=\"2\">What would you call some place where no one lives?<ul class=\"ul-choose-answer\"><li>a. Fatal</li><li>b. Abnormal</li><li>c. Wilderness</li><li>d. Dishonest</li></ul></li><li class=\"answer-the-questions-section\" answer-index=\"0\">Where would you most likely find a fish?<ul class=\"ul-choose-answer\"><li>a. In a pond</li><li>b. On a leaf</li><li>c. In the wilderness</li><li>d. On some bamboo</li></ul></li><li class=\"answer-the-questions-section\" answer-index=\"1\">People use flowers to ______.<ul class=\"ul-choose-answer\"><li>a. be a dwarf</li><li>b. make perfume</li><li>c. recite a song</li><li>d. read a manuscript</li></ul></li><li class=\"answer-the-questions-section\" answer-index=\"3\">What would someone sailing in the ocean use to know which way they were going?<ul class=\"ul-choose-answer\"><li>a. An ecosystem</li><li>b. Patience</li><li>c. A dialect</li><li>d. A compass</li></ul></li><li class=\"answer-the-questions-section\" answer-index=\"0\">Which of the following is a part of a plant?<ul class=\"ul-choose-answer\"><li>a. A blossom</li><li>b. A marsh</li><li>c. A proverb</li><li>d. A pursuit</li></ul></li></ol>", "sound": ""}, {"en": "Exercise 3", "story": "<h4>Choose the word that is the better fit for each blank.</h4><ol><li class=\"answer-the-questions-section-better-fit\"  answer-index=\"ecosystem / pond\"><span>ecosystem / pond</span><br/>Frogs are an important part of the __________, especially around a(n) __________.</li><li class=\"answer-the-questions-section-better-fit\"  answer-index=\"recited / dialect\"><span>dialect / recited</span><br/>When he __________ the poem in front the class, they could not understand him I because he spoke with a different __________.</li><li class=\"answer-the-questions-section-better-fit\"  answer-index=\"abnormal / dwarf\"><span>abnormal / dwarf</span><br/>They had never seen anything as __________ as this creature. It looked and dressed like a man, but the __________ was short and had a long nose.</li><li class=\"answer-the-questions-section-better-fit\"  answer-index=\"manuscript / impatient\"><span>impatient / manuscript</span><br/>The __________ was so old that the words were hard to read. Though she tried to I read it, she soon became __________ and put the old book away.</li><li class=\"answer-the-questions-section-better-fit\"  answer-index=\"proverbs / patience\"><span>patience / proverbs</span><br/>Many __________ try to teach lessons about human qualities such as honesty and __________.</li><li class=\"answer-the-questions-section-better-fit\"  answer-index=\"pursuit / marsh\"><span>marsh / pursuit</span><br/>The __________ through the __________ was very difficult because the ground was too wet to stand on.</li><li class=\"answer-the-questions-section-better-fit\"  answer-index=\"blossom / perfume\"><span>blossom / perfume</span><br/>She crushed the __________ and mixed it with some water so she could make the __________.</li><li class=\"answer-the-questions-section-better-fit\"  answer-index=\"dishonest / fatal\"><span>dishonest / fatal</span><br/>The label on the bottle was __________. It said that the powder didn&rsquo;t hurt children when it was actually __________ for them to consume.</li><li class=\"answer-the-questions-section-better-fit\"  answer-index=\"leaves / bamboo\"><span>bamboo / leaves</span><br/>The __________ that grow on the __________ are thick and hard to chew.</li><li class=\"answer-the-questions-section-better-fit\"  answer-index=\"wilderness / compass\"><span>compass / wilderness</span><br/>Because it is easy to lose your way in the __________, it&rsquo;s a good idea to bring a __________ with you.</li></ol>", "sound": ""}, {"en": "Answer Key", "story": "<div class=\"answer-key-part\">Exercise 1</div><div class=\"answer-part\"><strong>Part A</strong></div><ol><li class=\"answer-key\">c</li><li class=\"answer-key\">b</li><li class=\"answer-key\">a</li><li class=\"answer-key\">c</li><li class=\"answer-key\">d</li></ol><div class=\"answer-part\"><strong>Part B</strong></div><ol><li class=\"answer-key\">d</li><li class=\"answer-key\">a</li><li class=\"answer-key\">a</li><li class=\"answer-key\">b</li><li class=\"answer-key\">b</li></ol><div class=\"answer-key-only\">Exercise 2</div><ol><li class=\"answer-key\">c</li><li class=\"answer-key\">a</li><li class=\"answer-key\">b</li><li class=\"answer-key\">d</li><li class=\"answer-key\">a</li></ol><div class=\"answer-key-only\">Exercise 3</div><ol><li class=\"answer-key\">ecosystem, pond</li><li class=\"answer-key\">recited, dialect</li><li class=\"answer-key\">abnormal, dwarf</li><li class=\"answer-key\">manuscript, impatient</li><li class=\"answer-key\">proverbs, patience</li><li class=\"answer-key\">pursuit, marsh</li><li class=\"answer-key\">blossom, perfume</li><li class=\"answer-key\">dishonest, fatal</li><li class=\"answer-key\">leaves, bamboo</li><li class=\"answer-key\">wilderness, compass</li></ol>", "sound": ""}], "reading": [{"type": "story", "en": "Peter and the Dwarf", "story": "<p>Peter was a hunter. One day, he was in <strong class='idiom-tip' idx='17'>pursuit </strong>of a deer and became lost. He usually carried a <strong class='idiom-tip' idx='3'>compass </strong>with him when he went into the <strong class='idiom-tip' idx='19'>wilderness</strong>, but that day he left it at home.</p><p>As he walked, the forest began to look different. He didn&rsquo;t see any <strong class='idiom-tip' idx='1'>bamboo</strong>. Instead, there were bushes with long <strong class='idiom-tip' idx='10'>leaves</strong>. The <strong class='idiom-tip' idx='7'>ecosystem </strong>was now very <strong class='idiom-tip' idx='0'>abnormal</strong>. Peter knew he was in the Magic <strong class='idiom-tip' idx='12'>Marsh</strong>.</p><p>Now he was tired and thirsty. He was afraid. Being lost in the marsh could be <strong class='idiom-tip' idx='8'>fatal</strong>. When people entered it, they never came out.</p><p>At last, he found a <strong class='idiom-tip' idx='15'>pond</strong>. Flowers grew around it. The <strong class='idiom-tip' idx='2'>blossoms </strong>smelled like the best <strong class='idiom-tip' idx='14'>perfume</strong>. He felt relaxed so he drank some water and fell asleep. When he awoke, he saw an evil <strong class='idiom-tip' idx='6'>dwarf </strong>staring at him.</p><p>&ldquo; What are you doing here?&rdquo; it asked. The dwarf spoke in a strange <strong class='idiom-tip' idx='4'>dialect</strong>.</p><p>&ldquo; I&rsquo;m lost,&rdquo; said Peter. &ldquo; Can you help me?&rdquo;</p><p>&ldquo;Yes,&rdquo; it said, but Peter didn&rsquo;t know it was <strong class='idiom-tip' idx='5'>dishonest</strong>.</p><p>The dwarf took an old <strong class='idiom-tip' idx='11'>manuscript </strong>from his pocket. It was a magic map. &ldquo; Just <strong class='idiom-tip' idx='18'>recite </strong>the words at the bottom,&rdquo; the dwarf explained. &ldquo; It will show you how to get home.&rdquo;</p><p>&ldquo; Good,&rdquo; Peter said. He was <strong class='idiom-tip' idx='9'>impatient </strong>and quickly grabbed the map.</p><p>He recited the magic words, and a line appeared on the map. He walked for many days but never left the marsh. Finally, the map led him back to the pond. He walked in a circle!</p><p>The dwarf was still there. &ldquo; Here&rsquo;s a <strong class='idiom-tip' idx='16'>proverb </strong>for you to think about,&rdquo; it said, &ldquo; When patience is lost, the so are you.&rdquo;</p>", "vi": "", "image": "26282.jpg", "sound": "26282.mp3"}, {"type": "faq", "en": "Reading Comprehension", "story": "<h4>Part A: Mark each statement <span style=\"color:#ff0000;\">T</span> for true or <span style=\"color:#ff0000;\">F</span> for false. Rewrite the false statements to make them true.</h4><ol><li class=\"answer-the-questions-section-true-false\" tof=\"T\" fvalue=\"\">_____ Peter left his compass at home.<br/>__________</li><li class=\"answer-the-questions-section-true-false\" tof=\"F\" fvalue=\"When people entered the Magic Marsh, they never came out.\">_____ When people entered the Magic Marsh, they always came out.<br/>__________</li><li class=\"answer-the-questions-section-true-false\" tof=\"F\" fvalue=\"Peter drank some water and fell asleep.\">_____ Peter ate some flowers and fell asleep.<br/>__________</li><li class=\"answer-the-questions-section-true-false\" tof=\"T\" fvalue=\"\">_____ The dwarf spoke with a strange dialect.<br/>__________</li><li class=\"answer-the-questions-section-true-false\" tof=\"F\" fvalue=\"Peter didn’t know the dwarf was dishonest.\">_____ Peter knew the dwarf was dishonest.<br/>__________</li><li class=\"answer-the-questions-section-true-false\" tof=\"T\" fvalue=\"\">_____ The map led Peter back to the pond.<br/>__________</li></ol><h4>Part B: Answer the questions.</h4><ol><li class=\"answer-the-questions-section\" answer-index=\"0\">Why was Peter in the wilderness?<ul class=\"ul-choose-answer\"><li>a. He was in pursuit of a deer.</li><li>b. He was weak and hungry.</li><li>c. He was looking for the Magic Marsh.</li><li>d. He was lost.</li></ul></li><li class=\"answer-the-questions-section\" answer-index=\"2\">How did Peter know he was in the Magic March?<ul class=\"ul-choose-answer\"><li>a. There was a lot of bamboo.</li><li>b. There were no leaves.</li><li>c. The ecosystem was abnormal.</li><li>d. He smelled blossoms.</li></ul></li><li class=\"answer-the-questions-section\" answer-index=\"1\">What did the dwarf have that could help Peter escape the marsh?<ul class=\"ul-choose-answer\"><li>a. A bottle of perfume</li><li>b. A magic manuscript</li><li>c. A compass</li><li>d. Patience</li></ul></li><li class=\"answer-the-questions-section\" answer-index=\"1\">Why was Peter afraid of the Magic Marsh?<ul class=\"ul-choose-answer\"><li>a. He was impatient.</li><li>b. Being lost there could be fatal.</li><li>c. He was tired and thirsty.</li><li>d. There was an evil dwarf in it.</li></ul></li></ol>", "vi": ""}, {"en": "Answer Key", "story": "<div class=\"answer-key-only\">Reading Comprehension</div><div class=\"answer-part\"><strong>Part A</strong></div><ol><li class=\"answer-key\">T</li><li class=\"answer-key\">F / When people entered the Magic Marsh, they never came out.</li><li class=\"answer-key\">F / Peter drank some water and fell asleep.</li><li class=\"answer-key\">T</li><li class=\"answer-key\">F / Peter didn&rsquo;t know the dwarf was dishonest.</li><li class=\"answer-key\">T</li></ol><div class=\"answer-part\"><strong>Part B</strong></div><ol><li class=\"answer-key\">a</li><li class=\"answer-key\">c</li><li class=\"answer-key\">b</li><li class=\"answer-key\">b</li></ol>", "vi": ""}]}